msegat/__init__.py
msegat/base.py
msegat/client.py
msegat/configuration.py
msegat/exceptions/__init__.py
msegat/exceptions/api_exception.py
msegat/handlers/__init__.py
msegat/handlers/handler.py
msegat/handlers/msgs/__init__.py
msegat/handlers/msgs/send_sms.py
msegat/helpers/__init__.py
msegat/helpers/api_helper.py
msegat/http/__init__.py
msegat/http/http_client.py
msegat/http/http_context.py
msegat/http/http_method_enum.py
msegat/http/http_request.py
msegat/http/http_response.py
msegat/http/requests_client.py
msegat/http/auth/__init__.py
msegat/http/auth/api_token.py
msegat/requests/__init__.py
msegat/requests/gw/__init__.py
msegat/requests/gw/send_sms.py
msegat/responses/__init__.py
msegat/responses/gw/__init__.py
msegat/responses/gw/send_sms.py
tests/__init__.py
tests/send_sms.py
msegat-1.0.4.dist-info/LICENSE.txt
msegat-1.0.4.dist-info/METADATA
msegat-1.0.4.dist-info/WHEEL
msegat-1.0.4.dist-info/top_level.txt
msegat-1.0.4.dist-info/RECORD
