Metadata-Version: 2.1
Name: msegat
Version: 1.0.4
Summary: Msegat API client
Home-page: https://gitlab.com/abdroos/msegat
Author: Abdullah Alaidrous
Author-email: abd.alaidrous@gmail.com
Classifier: Programming Language :: Python :: 3
Classifier: License :: OSI Approved :: MIT License
Classifier: Operating System :: OS Independent
Requires-Python: >=3.6
License-File: LICENSE.txt
Requires-Dist: requests>=2.32.3
Requires-Dist: python-dateutil>=2.8.2
Requires-Dist: jsonpickle>=0.9.6
Requires-Dist: urllib3>=1.26.20
Requires-Dist: six>=1.16.0
